skeleton/warmup/MealyMachine.v
module MealyPattern(
	input        clock,
	input        i,
	output [1:0] o
);

//Unique binary representation for each state:
reg [1:0]  q;
reg [1:0]  t;

initial begin
	q = 2'b00;
	t = 2'b00;
end

always @(posedge clock) begin  // update at rising clock edge
	q[0] <= q[1];
	q[1] <= i;
end

always @* begin  // change the output combinatorially -> doe not depend on clock edge
	if (q[0] == 1 && q[1] == 0 && i==1) begin
		t = 2'b01;
	end
	else 
		if (q[0] == 0 && q[1] == 1 && i==0) begin
		t = 2'b10;
	end
		else 
		t = 2'b00;
end

assign o = t;

endmodule

module MealyPatternTestbench();

	reg i;
	reg clock;
	wire  [1:0] o;

	MealyPattern machine(.clock(clock), .i(i), .o(o));

	initial begin
		i = 0 ;
		clock = 0 ;
	end

	always
		#1
		clock = !clock;
	
	initial begin
		#2
		i = 1;
		#2
		i = 1;
		#2
		i = 0;
		#2
		i = 1;
		#2
		i = 0;
		#2
		i = 1;
		#2
		i = 0;
		#2
		i = 1;
		#2
		i = 1;
	end

	initial begin
		$dumpfile ("mealy.vcd");
		$dumpvars ;
	end

	initial
		#20 $finish;


	//  011

endmodule

skeleton/warmup/mealy.vcd
$date
	Sat Jun  3 20:44:46 2023
$end
$version
	Icarus Verilog
$end
$timescale
	1s
$end
$scope module MealyPatternTestbench $end
$var wire 2 ! o [1:0] $end
$var reg 1 " clock $end
$var reg 1 # i $end
$scope module machine $end
$var wire 1 " clock $end
$var wire 1 # i $end
$var wire 2 $ o [1:0] $end
$var reg 2 % q [1:0] $end
$var reg 2 & t [1:0] $end
$upscope $end
$upscope $end
$enddefinitions $end
#0
$dumpvars
b0 &
b0 %
b0 $
0#
0"
b0 !
$end
#1
1"
#2
0"
1#
#3
b10 %
1"
#4
0"
#5
b11 %
1"
#6
0"
0#
#7
b1 %
1"
#8
b1 !
b1 $
b1 &
0"
1#
#9
b0 !
b0 $
b0 &
b10 %
1"
#10
b10 !
b10 $
b10 &
0"
0#
#11
b0 !
b0 $
b0 &
b1 %
1"
#12
b1 !
b1 $
b1 &
0"
1#
#13
b0 !
b0 $
b0 &
b10 %
1"
#14
b10 !
b10 $
b10 &
0"
0#
#15
b0 !
b0 $
b0 &
b1 %
1"
#16
b1 !
b1 $
b1 &
0"
1#
#17
b0 !
b0 $
b0 &
b10 %
1"
#18
0"
#19
b11 %
1"
